pandasecharts/__init__.py
pandasecharts/echart.py
pandasecharts/configs/__init__.py
pandasecharts/configs/basic_cfg.py
pandasecharts/configs/chart_cfg.py
pandasecharts/core/__init__.py
pandasecharts/core/chart_tool.py
pandasecharts/core/data_tool.py
pandasecharts-0.5.dist-info/LICENSE
pandasecharts-0.5.dist-info/METADATA
pandasecharts-0.5.dist-info/WHEEL
pandasecharts-0.5.dist-info/top_level.txt
pandasecharts-0.5.dist-info/RECORD
