Metadata-Version: 2.1
Name: pandasecharts
Version: 0.5
Summary: Visualize your pandas data with one-line code
Home-page: https://github.com/gamersover/pandasecharts
Author: gamersover
Author-email: cmathking@gmail.com
Project-URL: Bug Reports, https://github.com/gamersover/pandasecharts/issues
Project-URL: Source, https://github.com/gamersover/pandasecharts
Keywords: pandas,echarts,data visualization
Classifier: Development Status :: 3 - Alpha
Classifier: Intended Audience :: Developers
Classifier: Topic :: Software Development :: Build Tools
Classifier: License :: OSI Approved :: MIT License
Classifier: Programming Language :: Python :: 3
Classifier: Programming Language :: Python :: 3.6
Classifier: Programming Language :: Python :: 3.7
Classifier: Programming Language :: Python :: 3.8
Classifier: Programming Language :: Python :: 3.9
Classifier: Programming Language :: Python :: 3.10
Classifier: Programming Language :: Python :: 3 :: Only
Requires-Python: >=3.6, <4
License-File: LICENSE
Requires-Dist: pandas
Requires-Dist: pyecharts (>=1.0.0)
